odoo/addons/test_base_time_window/README.rst
odoo/addons/test_base_time_window/__init__.py
odoo/addons/test_base_time_window/__manifest__.py
odoo/addons/test_base_time_window/i18n/ca.po
odoo/addons/test_base_time_window/i18n/es.po
odoo/addons/test_base_time_window/i18n/it.po
odoo/addons/test_base_time_window/i18n/test_base_time_window.pot
odoo/addons/test_base_time_window/models/__init__.py
odoo/addons/test_base_time_window/models/partner_time_window.py
odoo/addons/test_base_time_window/models/res_partner.py
odoo/addons/test_base_time_window/readme/CONTRIBUTORS.md
odoo/addons/test_base_time_window/readme/CREDITS.md
odoo/addons/test_base_time_window/readme/DESCRIPTION.md
odoo/addons/test_base_time_window/security/ir.model.access.xml
odoo/addons/test_base_time_window/static/description/icon.png
odoo/addons/test_base_time_window/static/description/index.html
odoo/addons/test_base_time_window/tests/__init__.py
odoo/addons/test_base_time_window/tests/test_base_time_window.py
odoo_addon_test_base_time_window-18.0.1.0.0.8.dist-info/METADATA
odoo_addon_test_base_time_window-18.0.1.0.0.8.dist-info/WHEEL
odoo_addon_test_base_time_window-18.0.1.0.0.8.dist-info/top_level.txt
odoo_addon_test_base_time_window-18.0.1.0.0.8.dist-info/RECORD
